[
	{
		"item_id": "8004",
		"item_name": "开拓者",
		"icon_url": "https://act-webstatic.mihoyo.com/darkmatter/hkrpg/prod_gf_cn/item_icon_73c59v/436e6776497b709428b4ba556731685d.png",
		"damage_type": "2",
		"rarity": "5",
		"avatar_base_type": "6",
		"max_level": 80,
		"cur_level": 1,
		"target_level": 0,
		"vertical_icon_url": ""
	},
	{
		"item_id": "8003",
		"item_name": "开拓者",
		"icon_url": "https://act-webstatic.mihoyo.com/darkmatter/hkrpg/prod_gf_cn/item_icon_73c59v/451aa124fa7af2186d75d9d699b01152.png",
		"damage_type": "2",
		"rarity": "5",
		"avatar_base_type": "6",
		"max_level": 80,
		"cur_level": 1,
		"target_level": 0,
		"vertical_icon_url": ""
	},
	{
		"item_id": "8002",
		"item_name": "开拓者",
		"icon_url": "https://act-webstatic.mihoyo.com/darkmatter/hkrpg/prod_gf_cn/item_icon_73c59v/9842fa7b6e4be74fa840747130cd72a9.png",
		"damage_type": "1",
		"rarity": "5",
		"avatar_base_type": "1",
		"max_level": 80,
		"cur_level": 1,
		"target_level": 0,
		"vertical_icon_url": ""
	},
	{
		"item_id": "8001",
		"item_name": "开拓者",
		"icon_url": "https://act-webstatic.mihoyo.com/darkmatter/hkrpg/prod_gf_cn/item_icon_73c59v/03ea77ee74c81948a83747b765eaac9e.png",
		"damage_type": "1",
		"rarity": "5",
		"avatar_base_type": "1",
		"max_level": 80,
		"cur_level": 1,
		"target_level": 0,
		"vertical_icon_url": ""
	},
	{
		"item_id": "1213",
		"item_name": "丹恒•饮月",
		"icon_url": "https://act-webstatic.mihoyo.com/darkmatter/hkrpg/prod_gf_cn/item_icon_73c59v/cc25500397b2b37969c1209245d847c7.png",
		"damage_type": "64",
		"rarity": "5",
		"avatar_base_type": "1",
		"max_level": 80,
		"cur_level": 1,
		"target_level": 0,
		"vertical_icon_url": ""
	},
	{
		"item_id": "1211",
		"item_name": "白露",
		"icon_url": "https://act-webstatic.mihoyo.com/darkmatter/hkrpg/prod_gf_cn/item_icon_73c59v/fbea2370603ecf963236b1fac085269e.png",
		"damage_type": "8",
		"rarity": "5",
		"avatar_base_type": "7",
		"max_level": 80,
		"cur_level": 1,
		"target_level": 0,
		"vertical_icon_url": ""
	},
	{
		"item_id": "1209",
		"item_name": "彦卿",
		"icon_url": "https://act-webstatic.mihoyo.com/darkmatter/hkrpg/prod_gf_cn/item_icon_73c59v/027e4b3562e4521078db158df84c65ab.png",
		"damage_type": "4",
		"rarity": "5",
		"avatar_base_type": "2",
		"max_level": 80,
		"cur_level": 1,
		"target_level": 0,
		"vertical_icon_url": ""
	},
	{
		"item_id": "1205",
		"item_name": "刃",
		"icon_url": "https://act-webstatic.mihoyo.com/darkmatter/hkrpg/prod_gf_cn/item_icon_73c59v/4bd32f4bcdeb82de32811b04ff135b9f.png",
		"damage_type": "16",
		"rarity": "5",
		"avatar_base_type": "1",
		"max_level": 80,
		"cur_level": 1,
		"target_level": 0,
		"vertical_icon_url": ""
	},
	{
		"item_id": "1204",
		"item_name": "景元",
		"icon_url": "https://act-webstatic.mihoyo.com/darkmatter/hkrpg/prod_gf_cn/item_icon_73c59v/b535a581e0dc0eadde87ed0314e6a5aa.png",
		"damage_type": "8",
		"rarity": "5",
		"avatar_base_type": "3",
		"max_level": 80,
		"cur_level": 1,
		"target_level": 0,
		"vertical_icon_url": ""
	},
	{
		"item_id": "1203",
		"item_name": "罗刹",
		"icon_url": "https://act-webstatic.mihoyo.com/darkmatter/hkrpg/prod_gf_cn/item_icon_73c59v/7262013fe8cd4fd05e83cac9e0f97c3d.png",
		"damage_type": "64",
		"rarity": "5",
		"avatar_base_type": "7",
		"max_level": 80,
		"cur_level": 1,
		"target_level": 0,
		"vertical_icon_url": ""
	},
	{
		"item_id": "1107",
		"item_name": "克拉拉",
		"icon_url": "https://act-webstatic.mihoyo.com/darkmatter/hkrpg/prod_gf_cn/item_icon_73c59v/461175fe19483ff586c9341d4caafd75.png",
		"damage_type": "1",
		"rarity": "5",
		"avatar_base_type": "1",
		"max_level": 80,
		"cur_level": 1,
		"target_level": 0,
		"vertical_icon_url": ""
	},
	{
		"item_id": "1104",
		"item_name": "杰帕德",
		"icon_url": "https://act-webstatic.mihoyo.com/darkmatter/hkrpg/prod_gf_cn/item_icon_73c59v/7dbf78d71b30e855bfb3a36794bb7304.png",
		"damage_type": "4",
		"rarity": "5",
		"avatar_base_type": "6",
		"max_level": 80,
		"cur_level": 1,
		"target_level": 0,
		"vertical_icon_url": ""
	},
	{
		"item_id": "1102",
		"item_name": "希儿",
		"icon_url": "https://act-webstatic.mihoyo.com/darkmatter/hkrpg/prod_gf_cn/item_icon_73c59v/07715c70f60c83b3b697257178c5ed33.png",
		"damage_type": "32",
		"rarity": "5",
		"avatar_base_type": "2",
		"max_level": 80,
		"cur_level": 1,
		"target_level": 0,
		"vertical_icon_url": ""
	},
	{
		"item_id": "1101",
		"item_name": "布洛妮娅",
		"icon_url": "https://act-webstatic.mihoyo.com/darkmatter/hkrpg/prod_gf_cn/item_icon_73c59v/22ad9c64fef1721f5e0a599fbd5accf5.png",
		"damage_type": "16",
		"rarity": "5",
		"avatar_base_type": "4",
		"max_level": 80,
		"cur_level": 1,
		"target_level": 0,
		"vertical_icon_url": ""
	},
	{
		"item_id": "1006",
		"item_name": "银狼",
		"icon_url": "https://act-webstatic.mihoyo.com/darkmatter/hkrpg/prod_gf_cn/item_icon_73c59v/6aebfe36a94c005446d936e15e457f65.png",
		"damage_type": "32",
		"rarity": "5",
		"avatar_base_type": "5",
		"max_level": 80,
		"cur_level": 1,
		"target_level": 0,
		"vertical_icon_url": ""
	},
	{
		"item_id": "1005",
		"item_name": "卡芙卡",
		"icon_url": "https://act-webstatic.mihoyo.com/darkmatter/hkrpg/prod_gf_cn/item_icon_73c59v/db83fd11db2bd84a343c4ceb075824b0.png",
		"damage_type": "8",
		"rarity": "5",
		"avatar_base_type": "5",
		"max_level": 80,
		"cur_level": 1,
		"target_level": 0,
		"vertical_icon_url": ""
	},
	{
		"item_id": "1004",
		"item_name": "瓦尔特",
		"icon_url": "https://act-webstatic.mihoyo.com/darkmatter/hkrpg/prod_gf_cn/item_icon_73c59v/df639bc92e711db3d62793c058c392e7.png",
		"damage_type": "64",
		"rarity": "5",
		"avatar_base_type": "5",
		"max_level": 80,
		"cur_level": 1,
		"target_level": 0,
		"vertical_icon_url": ""
	},
	{
		"item_id": "1003",
		"item_name": "姬子",
		"icon_url": "https://act-webstatic.mihoyo.com/darkmatter/hkrpg/prod_gf_cn/item_icon_73c59v/7a0f2b6a0560384e41d57056d1dacea3.png",
		"damage_type": "2",
		"rarity": "5",
		"avatar_base_type": "3",
		"max_level": 80,
		"cur_level": 1,
		"target_level": 0,
		"vertical_icon_url": ""
	},
	{
		"item_id": "1207",
		"item_name": "驭空",
		"icon_url": "https://act-webstatic.mihoyo.com/darkmatter/hkrpg/prod_gf_cn/item_icon_73c59v/ec4fbaf78304eb5c79fb8821caefa13f.png",
		"damage_type": "64",
		"rarity": "4",
		"avatar_base_type": "4",
		"max_level": 80,
		"cur_level": 1,
		"target_level": 0,
		"vertical_icon_url": ""
	},
	{
		"item_id": "1206",
		"item_name": "素裳",
		"icon_url": "https://act-webstatic.mihoyo.com/darkmatter/hkrpg/prod_gf_cn/item_icon_73c59v/f4604238ef8e1ce582230e5cae522e42.png",
		"damage_type": "1",
		"rarity": "4",
		"avatar_base_type": "2",
		"max_level": 80,
		"cur_level": 1,
		"target_level": 0,
		"vertical_icon_url": ""
	},
	{
		"item_id": "1202",
		"item_name": "停云",
		"icon_url": "https://act-webstatic.mihoyo.com/darkmatter/hkrpg/prod_gf_cn/item_icon_73c59v/4a0aed69dd5ae8cda98a0b39794640ce.png",
		"damage_type": "8",
		"rarity": "4",
		"avatar_base_type": "4",
		"max_level": 80,
		"cur_level": 1,
		"target_level": 0,
		"vertical_icon_url": ""
	},
	{
		"item_id": "1201",
		"item_name": "青雀",
		"icon_url": "https://act-webstatic.mihoyo.com/darkmatter/hkrpg/prod_gf_cn/item_icon_73c59v/83aebfec9840f8676acbe4df22ffaf3f.png",
		"damage_type": "32",
		"rarity": "4",
		"avatar_base_type": "3",
		"max_level": 80,
		"cur_level": 1,
		"target_level": 0,
		"vertical_icon_url": ""
	},
	{
		"item_id": "1111",
		"item_name": "卢卡",
		"icon_url": "https://act-webstatic.mihoyo.com/darkmatter/hkrpg/prod_gf_cn/item_icon_73c59v/a92662cd488c582162a2bb8ef4b29e37.png",
		"damage_type": "1",
		"rarity": "4",
		"avatar_base_type": "5",
		"max_level": 80,
		"cur_level": 1,
		"target_level": 0,
		"vertical_icon_url": ""
	},
	{
		"item_id": "1109",
		"item_name": "虎克",
		"icon_url": "https://act-webstatic.mihoyo.com/darkmatter/hkrpg/prod_gf_cn/item_icon_73c59v/5d42560bceb4a98dc5da1a5ee5c8f84f.png",
		"damage_type": "2",
		"rarity": "4",
		"avatar_base_type": "1",
		"max_level": 80,
		"cur_level": 1,
		"target_level": 0,
		"vertical_icon_url": ""
	},
	{
		"item_id": "1108",
		"item_name": "桑博",
		"icon_url": "https://act-webstatic.mihoyo.com/darkmatter/hkrpg/prod_gf_cn/item_icon_73c59v/5d12639b5f7635837ec5087af174ceb2.png",
		"damage_type": "16",
		"rarity": "4",
		"avatar_base_type": "5",
		"max_level": 80,
		"cur_level": 1,
		"target_level": 0,
		"vertical_icon_url": ""
	},
	{
		"item_id": "1106",
		"item_name": "佩拉",
		"icon_url": "https://act-webstatic.mihoyo.com/darkmatter/hkrpg/prod_gf_cn/item_icon_73c59v/b599a6cd18977ebca4589ec73e06dddb.png",
		"damage_type": "4",
		"rarity": "4",
		"avatar_base_type": "5",
		"max_level": 80,
		"cur_level": 1,
		"target_level": 0,
		"vertical_icon_url": ""
	},
	{
		"item_id": "1105",
		"item_name": "娜塔莎",
		"icon_url": "https://act-webstatic.mihoyo.com/darkmatter/hkrpg/prod_gf_cn/item_icon_73c59v/a936b157276af866d6bec64d4e500d3f.png",
		"damage_type": "1",
		"rarity": "4",
		"avatar_base_type": "7",
		"max_level": 80,
		"cur_level": 1,
		"target_level": 0,
		"vertical_icon_url": ""
	},
	{
		"item_id": "1103",
		"item_name": "希露瓦",
		"icon_url": "https://act-webstatic.mihoyo.com/darkmatter/hkrpg/prod_gf_cn/item_icon_73c59v/a36d5e68945486e851387f2946d59cb4.png",
		"damage_type": "8",
		"rarity": "4",
		"avatar_base_type": "3",
		"max_level": 80,
		"cur_level": 1,
		"target_level": 0,
		"vertical_icon_url": ""
	},
	{
		"item_id": "1013",
		"item_name": "黑塔",
		"icon_url": "https://act-webstatic.mihoyo.com/darkmatter/hkrpg/prod_gf_cn/item_icon_73c59v/b73048cb03e6bf1e07a21f8a8f291a1e.png",
		"damage_type": "4",
		"rarity": "4",
		"avatar_base_type": "3",
		"max_level": 80,
		"cur_level": 1,
		"target_level": 0,
		"vertical_icon_url": ""
	},
	{
		"item_id": "1009",
		"item_name": "艾丝妲",
		"icon_url": "https://act-webstatic.mihoyo.com/darkmatter/hkrpg/prod_gf_cn/item_icon_73c59v/6d2223e6fbe427b6f1c73348b01ecfeb.png",
		"damage_type": "2",
		"rarity": "4",
		"avatar_base_type": "4",
		"max_level": 80,
		"cur_level": 1,
		"target_level": 0,
		"vertical_icon_url": ""
	},
	{
		"item_id": "1008",
		"item_name": "阿兰",
		"icon_url": "https://act-webstatic.mihoyo.com/darkmatter/hkrpg/prod_gf_cn/item_icon_73c59v/41d85fc85b6c2250404961d2896d6b81.png",
		"damage_type": "8",
		"rarity": "4",
		"avatar_base_type": "1",
		"max_level": 80,
		"cur_level": 1,
		"target_level": 0,
		"vertical_icon_url": ""
	},
	{
		"item_id": "1002",
		"item_name": "丹恒",
		"icon_url": "https://act-webstatic.mihoyo.com/darkmatter/hkrpg/prod_gf_cn/item_icon_73c59v/9493befbfac1f388c87a8e4d753a66de.png",
		"damage_type": "16",
		"rarity": "4",
		"avatar_base_type": "2",
		"max_level": 80,
		"cur_level": 1,
		"target_level": 0,
		"vertical_icon_url": "http://立绘1002"
	},
	{
		"item_id": "1001",
		"item_name": "三月七",
		"icon_url": "https://act-webstatic.mihoyo.com/darkmatter/hkrpg/prod_gf_cn/item_icon_73c59v/c4b2b8a673cde6bace004f7a14bbae31.png",
		"damage_type": "4",
		"rarity": "4",
		"avatar_base_type": "6",
		"max_level": 80,
		"cur_level": 1,
		"target_level": 0,
		"vertical_icon_url": "http://立绘1001"
	}
]