[
	{
		"version": "2.0.2",
		"items": [
			{
				"itemId": 1306,
				"damageType": "32",
				"element": "quantum",
				"imageUrl": "/darkmatter/hkrpg/prod_gf_cn/item_icon_u642mb/ccca19b6318351ee87ad26bb8141a8a0.png",
				"rankType": 5,
				"avatarBaseType": "4",
				"weaponType": "shaman",
				"itemType": "Character",
				"name": "花火"
			},
			{
				"itemId": 1204,
				"damageType": "8",
				"element": "thunder",
				"imageUrl": "/darkmatter/hkrpg/prod_gf_cn/item_icon_u642mb/9b9fcf81d9af7bb27246eca1a3184728.png",
				"rankType": 5,
				"avatarBaseType": "3",
				"weaponType": "mage",
				"itemType": "Character",
				"name": "景元"
			},
			{
				"itemId": 1108,
				"damageType": "16",
				"element": "wind",
				"imageUrl": "/darkmatter/hkrpg/prod_gf_cn/item_icon_u642mb/c412ec7973f74c99b0bf66a0055b0167.png",
				"rankType": 4,
				"avatarBaseType": "5",
				"weaponType": "warlock",
				"itemType": "Character",
				"name": "桑博"
			},
			{
				"itemId": 1201,
				"damageType": "32",
				"element": "quantum",
				"imageUrl": "/darkmatter/hkrpg/prod_gf_cn/item_icon_u642mb/b63a39d775e1140d587c743557aad68b.png",
				"rankType": 4,
				"avatarBaseType": "3",
				"weaponType": "mage",
				"itemType": "Character",
				"name": "青雀"
			},
			{
				"itemId": 1215,
				"damageType": "1",
				"element": "physical",
				"imageUrl": "/darkmatter/hkrpg/prod_gf_cn/item_icon_u642mb/9d4cb2f16fffbc72fabea36bd8674fe0.png",
				"rankType": 4,
				"avatarBaseType": "4",
				"weaponType": "shaman",
				"itemType": "Character",
				"name": "寒鸦"
			}
		],
		"start": "2024-02-29 12:00:00",
		"end": "2024-03-26 14:59:59"
	},
	{
		"version": "2.0.1",
		"items": [
			{
				"itemId": 1307,
				"damageType": "16",
				"element": "wind",
				"imageUrl": "/darkmatter/hkrpg/prod_gf_cn/item_icon_u642mb/03229f12f76a539831f5383a9e0399df.png",
				"rankType": 5,
				"avatarBaseType": "5",
				"weaponType": "warlock",
				"itemType": "Character",
				"name": "黑天鹅"
			},
			{
				"itemId": 1213,
				"damageType": "64",
				"element": "imaginary",
				"imageUrl": "/darkmatter/hkrpg/prod_gf_cn/item_icon_u642mb/1e3152ed8ec5ea025f6f7ff7e3436730.png",
				"rankType": 5,
				"avatarBaseType": "1",
				"weaponType": "warrior",
				"itemType": "Character",
				"name": "丹恒•饮月"
			},
			{
				"itemId": 1312,
				"damageType": "4",
				"element": "ice",
				"imageUrl": "/darkmatter/hkrpg/prod_gf_cn/item_icon_u642mb/331de460d1b0671b33fd81556e3d609d.png",
				"rankType": 4,
				"avatarBaseType": "1",
				"weaponType": "warrior",
				"itemType": "Character",
				"name": "米沙"
			},
			{
				"itemId": 1202,
				"damageType": "8",
				"element": "thunder",
				"imageUrl": "/darkmatter/hkrpg/prod_gf_cn/item_icon_u642mb/d287e9e79d0b7fcc87a942fd10ed5d5b.png",
				"rankType": 4,
				"avatarBaseType": "4",
				"weaponType": "shaman",
				"itemType": "Character",
				"name": "停云"
			},
			{
				"itemId": 1210,
				"damageType": "2",
				"element": "fire",
				"imageUrl": "/darkmatter/hkrpg/prod_gf_cn/item_icon_u642mb/9e9811d9bbaddac8544f288da4054efc.png",
				"rankType": 4,
				"avatarBaseType": "5",
				"weaponType": "warlock",
				"itemType": "Character",
				"name": "桂乃芬"
			}
		],
		"start": "2024-02-06 06:00:00",
		"end": "2024-02-29 11:59:59"
	},
	{
		"version": "1.6.2",
		"items": [
			{
				"itemId": 1305,
				"damageType": "64",
				"element": "imaginary",
				"imageUrl": "/darkmatter/hkrpg/prod_gf_cn/item_icon_u642mb/36074c5f849b436698ee7c4e3c312efc.png",
				"rankType": 5,
				"avatarBaseType": "2",
				"weaponType": "rogue",
				"itemType": "Character",
				"name": "真理医生"
			},
			{
				"itemId": 1005,
				"damageType": "8",
				"element": "thunder",
				"imageUrl": "/darkmatter/hkrpg/prod_gf_cn/item_icon_u642mb/d7a960d151d792642abbc1555303aadd.png",
				"rankType": 5,
				"avatarBaseType": "5",
				"weaponType": "warlock",
				"itemType": "Character",
				"name": "卡芙卡"
			},
			{
				"itemId": 1206,
				"damageType": "1",
				"element": "physical",
				"imageUrl": "/darkmatter/hkrpg/prod_gf_cn/item_icon_u642mb/6f8deffb935e0baa68463ad6d6ecab9f.png",
				"rankType": 4,
				"avatarBaseType": "2",
				"weaponType": "rogue",
				"itemType": "Character",
				"name": "素裳"
			},
			{
				"itemId": 1105,
				"damageType": "1",
				"element": "physical",
				"imageUrl": "/darkmatter/hkrpg/prod_gf_cn/item_icon_u642mb/2c02c20be78028dc850682fe67ed5a2d.png",
				"rankType": 4,
				"avatarBaseType": "7",
				"weaponType": "priest",
				"itemType": "Character",
				"name": "娜塔莎"
			},
			{
				"itemId": 1109,
				"damageType": "2",
				"element": "fire",
				"imageUrl": "/darkmatter/hkrpg/prod_gf_cn/item_icon_u642mb/2768214036f435a3204cbde150082a0d.png",
				"rankType": 4,
				"avatarBaseType": "1",
				"weaponType": "warrior",
				"itemType": "Character",
				"name": "虎克"
			}
		],
		"start": "2024-01-17 12:00:00",
		"end": "2024-02-05 14:59:59"
	},
	{
		"version": "1.6.1",
		"items": [
			{
				"itemId": 1303,
				"damageType": "4",
				"element": "ice",
				"imageUrl": "/darkmatter/hkrpg/prod_gf_cn/item_icon_u642mb/7f62cb2f0e4b263bedec5f38d42b8d71.png",
				"rankType": 5,
				"avatarBaseType": "4",
				"weaponType": "shaman",
				"itemType": "Character",
				"name": "阮•梅"
			},
			{
				"itemId": 1205,
				"damageType": "16",
				"element": "wind",
				"imageUrl": "/darkmatter/hkrpg/prod_gf_cn/item_icon_u642mb/55b07180706a7703dee6ddecf0eabe3e.png",
				"rankType": 5,
				"avatarBaseType": "1",
				"weaponType": "warrior",
				"itemType": "Character",
				"name": "刃"
			},
			{
				"itemId": 1214,
				"damageType": "32",
				"element": "quantum",
				"imageUrl": "/darkmatter/hkrpg/prod_gf_cn/item_icon_u642mb/14dfc68122e10d0d6914094d2372f625.png",
				"rankType": 4,
				"avatarBaseType": "1",
				"weaponType": "warrior",
				"itemType": "Character",
				"name": "雪衣"
			},
			{
				"itemId": 1001,
				"damageType": "4",
				"element": "ice",
				"imageUrl": "/darkmatter/hkrpg/prod_gf_cn/item_icon_u642mb/77cdb978c7b10728bf4aa1e4e895be34.png",
				"rankType": 4,
				"avatarBaseType": "6",
				"weaponType": "knight",
				"itemType": "Character",
				"name": "三月七"
			},
			{
				"itemId": 1202,
				"damageType": "8",
				"element": "thunder",
				"imageUrl": "/darkmatter/hkrpg/prod_gf_cn/item_icon_u642mb/d287e9e79d0b7fcc87a942fd10ed5d5b.png",
				"rankType": 4,
				"avatarBaseType": "4",
				"weaponType": "shaman",
				"itemType": "Character",
				"name": "停云"
			}
		],
		"start": "2023-12-27 06:00:00",
		"end": "2024-01-17 11:59:59"
	},
	{
		"version": "1.5.2",
		"items": [
			{
				"itemId": 1302,
				"damageType": "1",
				"element": "physical",
				"imageUrl": "/darkmatter/hkrpg/prod_gf_cn/item_icon_u642mb/effc56211daaa7b038cda67d18cd2885.png",
				"rankType": 5,
				"avatarBaseType": "3",
				"weaponType": "mage",
				"itemType": "Character",
				"name": "银枝"
			},
			{
				"itemId": 1006,
				"damageType": "32",
				"element": "quantum",
				"imageUrl": "/darkmatter/hkrpg/prod_gf_cn/item_icon_u642mb/9220e157521748aec2327acd54b04d81.png",
				"rankType": 5,
				"avatarBaseType": "5",
				"weaponType": "warlock",
				"itemType": "Character",
				"name": "银狼"
			},
			{
				"itemId": 1215,
				"damageType": "1",
				"element": "physical",
				"imageUrl": "/darkmatter/hkrpg/prod_gf_cn/item_icon_u642mb/9d4cb2f16fffbc72fabea36bd8674fe0.png",
				"rankType": 4,
				"avatarBaseType": "4",
				"weaponType": "shaman",
				"itemType": "Character",
				"name": "寒鸦"
			},
			{
				"itemId": 1110,
				"damageType": "32",
				"element": "quantum",
				"imageUrl": "/darkmatter/hkrpg/prod_gf_cn/item_icon_u642mb/b3cad842e30b2e6eb2fd20d0d6271162.png",
				"rankType": 4,
				"avatarBaseType": "7",
				"weaponType": "priest",
				"itemType": "Character",
				"name": "玲可"
			},
			{
				"itemId": 1009,
				"damageType": "2",
				"element": "fire",
				"imageUrl": "/darkmatter/hkrpg/prod_gf_cn/item_icon_u642mb/69d4eb74adb9c8de2de89ed1c30d9cbe.png",
				"rankType": 4,
				"avatarBaseType": "4",
				"weaponType": "shaman",
				"itemType": "Character",
				"name": "艾丝妲"
			}
		],
		"start": "2023-12-06 12:00:00",
		"end": "2023-12-26 14:59:59"
	},
	{
		"version": "1.5.1",
		"items": [
			{
				"itemId": 1217,
				"damageType": "16",
				"element": "wind",
				"imageUrl": "/darkmatter/hkrpg/prod_gf_cn/item_icon_u642mb/8ec1421b23411c61e1eb3ff39f0a1e0d.png",
				"rankType": 5,
				"avatarBaseType": "7",
				"weaponType": "priest",
				"itemType": "Character",
				"name": "藿藿"
			},
			{
				"itemId": 1002,
				"damageType": "16",
				"element": "wind",
				"imageUrl": "/darkmatter/hkrpg/prod_gf_cn/item_icon_u642mb/151d92fc7e581b6562fc4cc4a2549788.png",
				"rankType": 4,
				"avatarBaseType": "2",
				"weaponType": "rogue",
				"itemType": "Character",
				"name": "丹恒"
			},
			{
				"itemId": 1008,
				"damageType": "8",
				"element": "thunder",
				"imageUrl": "/darkmatter/hkrpg/prod_gf_cn/item_icon_u642mb/b5b9ad4717258d1f7b6b21364e3be4a5.png",
				"rankType": 4,
				"avatarBaseType": "1",
				"weaponType": "warrior",
				"itemType": "Character",
				"name": "阿兰"
			},
			{
				"itemId": 1103,
				"damageType": "8",
				"element": "thunder",
				"imageUrl": "/darkmatter/hkrpg/prod_gf_cn/item_icon_u642mb/65f2e71359c3b6c51545d44ce88c265d.png",
				"rankType": 4,
				"avatarBaseType": "3",
				"weaponType": "mage",
				"itemType": "Character",
				"name": "希露瓦"
			}
		],
		"start": "2023-11-15 06:00:00",
		"end": "2023-12-06 11:59:59"
	},
	{
		"version": "1.4.2",
		"items": [
			{
				"itemId": 1112,
				"damageType": "2",
				"element": "fire",
				"imageUrl": "/darkmatter/hkrpg/prod_gf_cn/item_icon_u642mb/791d25b24077917ffa5671bc7a40e327.png",
				"rankType": 5,
				"avatarBaseType": "2",
				"weaponType": "rogue",
				"itemType": "Character",
				"name": "托帕&账账"
			},
			{
				"itemId": 1102,
				"damageType": "32",
				"element": "quantum",
				"imageUrl": "/darkmatter/hkrpg/prod_gf_cn/item_icon_u642mb/ca06f18257659c28762f427edfa81c8d.png",
				"rankType": 5,
				"avatarBaseType": "2",
				"weaponType": "rogue",
				"itemType": "Character",
				"name": "希儿"
			},
			{
				"itemId": 1210,
				"damageType": "2",
				"element": "fire",
				"imageUrl": "/darkmatter/hkrpg/prod_gf_cn/item_icon_u642mb/9e9811d9bbaddac8544f288da4054efc.png",
				"rankType": 4,
				"avatarBaseType": "5",
				"weaponType": "warlock",
				"itemType": "Character",
				"name": "桂乃芬"
			},
			{
				"itemId": 1111,
				"damageType": "1",
				"element": "physical",
				"imageUrl": "/darkmatter/hkrpg/prod_gf_cn/item_icon_u642mb/862e711b6c99d37bdb9f118edd38bd37.png",
				"rankType": 4,
				"avatarBaseType": "5",
				"weaponType": "warlock",
				"itemType": "Character",
				"name": "卢卡"
			},
			{
				"itemId": 1206,
				"damageType": "1",
				"element": "physical",
				"imageUrl": "/darkmatter/hkrpg/prod_gf_cn/item_icon_u642mb/6f8deffb935e0baa68463ad6d6ecab9f.png",
				"rankType": 4,
				"avatarBaseType": "2",
				"weaponType": "rogue",
				"itemType": "Character",
				"name": "素裳"
			}
		],
		"start": "2023-10-27 12:00:00",
		"end": "2023-11-14 14:59:59"
	},
	{
		"version": "1.4.1",
		"items": [
			{
				"itemId": 1212,
				"damageType": "4",
				"element": "ice",
				"imageUrl": "/darkmatter/hkrpg/prod_gf_cn/item_icon_u642mb/f35bed80b5debb79aaf1f860691e9933.png",
				"rankType": 5,
				"avatarBaseType": "1",
				"weaponType": "warrior",
				"itemType": "Character",
				"name": "镜流"
			},
			{
				"itemId": 1202,
				"damageType": "8",
				"element": "thunder",
				"imageUrl": "/darkmatter/hkrpg/prod_gf_cn/item_icon_u642mb/d287e9e79d0b7fcc87a942fd10ed5d5b.png",
				"rankType": 4,
				"avatarBaseType": "4",
				"weaponType": "shaman",
				"itemType": "Character",
				"name": "停云"
			},
			{
				"itemId": 1201,
				"damageType": "32",
				"element": "quantum",
				"imageUrl": "/darkmatter/hkrpg/prod_gf_cn/item_icon_u642mb/b63a39d775e1140d587c743557aad68b.png",
				"rankType": 4,
				"avatarBaseType": "3",
				"weaponType": "mage",
				"itemType": "Character",
				"name": "青雀"
			},
			{
				"itemId": 1108,
				"damageType": "16",
				"element": "wind",
				"imageUrl": "/darkmatter/hkrpg/prod_gf_cn/item_icon_u642mb/c412ec7973f74c99b0bf66a0055b0167.png",
				"rankType": 4,
				"avatarBaseType": "5",
				"weaponType": "warlock",
				"itemType": "Character",
				"name": "桑博"
			}
		],
		"start": "2023-10-11 06:00:00",
		"end": "2023-10-27 11:59:59"
	},
	{
		"version": "1.3.2",
		"items": [
			{
				"itemId": 1208,
				"damageType": "32",
				"element": "quantum",
				"imageUrl": "/darkmatter/hkrpg/prod_gf_cn/item_icon_u642mb/88856e597e0b02848465a3344a6e5a51.png",
				"rankType": 5,
				"avatarBaseType": "6",
				"weaponType": "knight",
				"itemType": "Character",
				"name": "符玄"
			},
			{
				"itemId": 1110,
				"damageType": "32",
				"element": "quantum",
				"imageUrl": "/darkmatter/hkrpg/prod_gf_cn/item_icon_u642mb/b3cad842e30b2e6eb2fd20d0d6271162.png",
				"rankType": 4,
				"avatarBaseType": "7",
				"weaponType": "priest",
				"itemType": "Character",
				"name": "玲可"
			},
			{
				"itemId": 1109,
				"damageType": "2",
				"element": "fire",
				"imageUrl": "/darkmatter/hkrpg/prod_gf_cn/item_icon_u642mb/2768214036f435a3204cbde150082a0d.png",
				"rankType": 4,
				"avatarBaseType": "1",
				"weaponType": "warrior",
				"itemType": "Character",
				"name": "虎克"
			},
			{
				"itemId": 1106,
				"damageType": "4",
				"element": "ice",
				"imageUrl": "/darkmatter/hkrpg/prod_gf_cn/item_icon_u642mb/0b49824fcc632e03f73c924fcf5cd313.png",
				"rankType": 4,
				"avatarBaseType": "5",
				"weaponType": "warlock",
				"itemType": "Character",
				"name": "佩拉"
			}
		],
		"start": "2023-09-20 12:00:00",
		"end": "2023-10-10 14:59:59"
	},
	{
		"version": "1.3.1",
		"items": [
			{
				"itemId": 1213,
				"damageType": "64",
				"element": "imaginary",
				"imageUrl": "/darkmatter/hkrpg/prod_gf_cn/item_icon_u642mb/1e3152ed8ec5ea025f6f7ff7e3436730.png",
				"rankType": 5,
				"avatarBaseType": "1",
				"weaponType": "warrior",
				"itemType": "Character",
				"name": "丹恒•饮月"
			},
			{
				"itemId": 1207,
				"damageType": "64",
				"element": "imaginary",
				"imageUrl": "/darkmatter/hkrpg/prod_gf_cn/item_icon_u642mb/5059de2b1befff427a9cdc057e34c923.png",
				"rankType": 4,
				"avatarBaseType": "4",
				"weaponType": "shaman",
				"itemType": "Character",
				"name": "驭空"
			},
			{
				"itemId": 1009,
				"damageType": "2",
				"element": "fire",
				"imageUrl": "/darkmatter/hkrpg/prod_gf_cn/item_icon_u642mb/69d4eb74adb9c8de2de89ed1c30d9cbe.png",
				"rankType": 4,
				"avatarBaseType": "4",
				"weaponType": "shaman",
				"itemType": "Character",
				"name": "艾丝妲"
			},
			{
				"itemId": 1001,
				"damageType": "4",
				"element": "ice",
				"imageUrl": "/darkmatter/hkrpg/prod_gf_cn/item_icon_u642mb/77cdb978c7b10728bf4aa1e4e895be34.png",
				"rankType": 4,
				"avatarBaseType": "6",
				"weaponType": "knight",
				"itemType": "Character",
				"name": "三月七"
			}
		],
		"start": "2023-08-30 06:00:00",
		"end": "2023-09-20 11:59:59"
	},
	{
		"version": "1.2.2",
		"items": [
			{
				"itemId": 1005,
				"damageType": "8",
				"element": "thunder",
				"imageUrl": "/darkmatter/hkrpg/prod_gf_cn/item_icon_u642mb/d7a960d151d792642abbc1555303aadd.png",
				"rankType": 5,
				"avatarBaseType": "5",
				"weaponType": "warlock",
				"itemType": "Character",
				"name": "卡芙卡"
			},
			{
				"itemId": 1111,
				"damageType": "1",
				"element": "physical",
				"imageUrl": "/darkmatter/hkrpg/prod_gf_cn/item_icon_u642mb/862e711b6c99d37bdb9f118edd38bd37.png",
				"rankType": 4,
				"avatarBaseType": "5",
				"weaponType": "warlock",
				"itemType": "Character",
				"name": "卢卡"
			},
			{
				"itemId": 1108,
				"damageType": "16",
				"element": "wind",
				"imageUrl": "/darkmatter/hkrpg/prod_gf_cn/item_icon_u642mb/c412ec7973f74c99b0bf66a0055b0167.png",
				"rankType": 4,
				"avatarBaseType": "5",
				"weaponType": "warlock",
				"itemType": "Character",
				"name": "桑博"
			},
			{
				"itemId": 1103,
				"damageType": "8",
				"element": "thunder",
				"imageUrl": "/darkmatter/hkrpg/prod_gf_cn/item_icon_u642mb/65f2e71359c3b6c51545d44ce88c265d.png",
				"rankType": 4,
				"avatarBaseType": "3",
				"weaponType": "mage",
				"itemType": "Character",
				"name": "希露瓦"
			}
		],
		"start": "2023-08-09 12:00:00",
		"end": "2023-08-29 14:59:59"
	},
	{
		"version": "1.2.1",
		"items": [
			{
				"itemId": 1205,
				"damageType": "16",
				"element": "wind",
				"imageUrl": "/darkmatter/hkrpg/prod_gf_cn/item_icon_u642mb/55b07180706a7703dee6ddecf0eabe3e.png",
				"rankType": 5,
				"avatarBaseType": "1",
				"weaponType": "warrior",
				"itemType": "Character",
				"name": "刃"
			},
			{
				"itemId": 1008,
				"damageType": "8",
				"element": "thunder",
				"imageUrl": "/darkmatter/hkrpg/prod_gf_cn/item_icon_u642mb/b5b9ad4717258d1f7b6b21364e3be4a5.png",
				"rankType": 4,
				"avatarBaseType": "1",
				"weaponType": "warrior",
				"itemType": "Character",
				"name": "阿兰"
			},
			{
				"itemId": 1105,
				"damageType": "1",
				"element": "physical",
				"imageUrl": "/darkmatter/hkrpg/prod_gf_cn/item_icon_u642mb/2c02c20be78028dc850682fe67ed5a2d.png",
				"rankType": 4,
				"avatarBaseType": "7",
				"weaponType": "priest",
				"itemType": "Character",
				"name": "娜塔莎"
			},
			{
				"itemId": 1206,
				"damageType": "1",
				"element": "physical",
				"imageUrl": "/darkmatter/hkrpg/prod_gf_cn/item_icon_u642mb/6f8deffb935e0baa68463ad6d6ecab9f.png",
				"rankType": 4,
				"avatarBaseType": "2",
				"weaponType": "rogue",
				"itemType": "Character",
				"name": "素裳"
			}
		],
		"start": "2023-07-19 06:00:00",
		"end": "2023-08-09 11:59:59"
	},
	{
		"version": "1.1.2",
		"items": [
			{
				"itemId": 1203,
				"damageType": "64",
				"element": "imaginary",
				"imageUrl": "/darkmatter/hkrpg/prod_gf_cn/item_icon_u642mb/f6cd2b655edbc1c2fb6029230d04aeb8.png",
				"rankType": 5,
				"avatarBaseType": "7",
				"weaponType": "priest",
				"itemType": "Character",
				"name": "罗刹"
			},
			{
				"itemId": 1207,
				"damageType": "64",
				"element": "imaginary",
				"imageUrl": "/darkmatter/hkrpg/prod_gf_cn/item_icon_u642mb/5059de2b1befff427a9cdc057e34c923.png",
				"rankType": 4,
				"avatarBaseType": "4",
				"weaponType": "shaman",
				"itemType": "Character",
				"name": "驭空"
			},
			{
				"itemId": 1106,
				"damageType": "4",
				"element": "ice",
				"imageUrl": "/darkmatter/hkrpg/prod_gf_cn/item_icon_u642mb/0b49824fcc632e03f73c924fcf5cd313.png",
				"rankType": 4,
				"avatarBaseType": "5",
				"weaponType": "warlock",
				"itemType": "Character",
				"name": "佩拉"
			},
			{
				"itemId": 1201,
				"damageType": "32",
				"element": "quantum",
				"imageUrl": "/darkmatter/hkrpg/prod_gf_cn/item_icon_u642mb/b63a39d775e1140d587c743557aad68b.png",
				"rankType": 4,
				"avatarBaseType": "3",
				"weaponType": "mage",
				"itemType": "Character",
				"name": "青雀"
			}
		],
		"start": "2023-06-28 12:00:00",
		"end": "2023-07-18 14:59:59"
	},
	{
		"version": "1.1.1",
		"items": [
			{
				"itemId": 1006,
				"damageType": "32",
				"element": "quantum",
				"imageUrl": "/darkmatter/hkrpg/prod_gf_cn/item_icon_u642mb/9220e157521748aec2327acd54b04d81.png",
				"rankType": 5,
				"avatarBaseType": "5",
				"weaponType": "warlock",
				"itemType": "Character",
				"name": "银狼"
			},
			{
				"itemId": 1002,
				"damageType": "16",
				"element": "wind",
				"imageUrl": "/darkmatter/hkrpg/prod_gf_cn/item_icon_u642mb/151d92fc7e581b6562fc4cc4a2549788.png",
				"rankType": 4,
				"avatarBaseType": "2",
				"weaponType": "rogue",
				"itemType": "Character",
				"name": "丹恒"
			},
			{
				"itemId": 1009,
				"damageType": "2",
				"element": "fire",
				"imageUrl": "/darkmatter/hkrpg/prod_gf_cn/item_icon_u642mb/69d4eb74adb9c8de2de89ed1c30d9cbe.png",
				"rankType": 4,
				"avatarBaseType": "4",
				"weaponType": "shaman",
				"itemType": "Character",
				"name": "艾丝妲"
			},
			{
				"itemId": 1103,
				"damageType": "8",
				"element": "thunder",
				"imageUrl": "/darkmatter/hkrpg/prod_gf_cn/item_icon_u642mb/65f2e71359c3b6c51545d44ce88c265d.png",
				"rankType": 4,
				"avatarBaseType": "3",
				"weaponType": "mage",
				"itemType": "Character",
				"name": "希露瓦"
			}
		],
		"start": "2023-06-07 06:00:00",
		"end": "2023-06-28 11:59:59"
	},
	{
		"version": "1.0.2",
		"items": [
			{
				"itemId": 1204,
				"damageType": "8",
				"element": "thunder",
				"imageUrl": "/darkmatter/hkrpg/prod_gf_cn/item_icon_u642mb/9b9fcf81d9af7bb27246eca1a3184728.png",
				"rankType": 5,
				"avatarBaseType": "3",
				"weaponType": "mage",
				"itemType": "Character",
				"name": "景元"
			},
			{
				"itemId": 1202,
				"damageType": "8",
				"element": "thunder",
				"imageUrl": "/darkmatter/hkrpg/prod_gf_cn/item_icon_u642mb/d287e9e79d0b7fcc87a942fd10ed5d5b.png",
				"rankType": 4,
				"avatarBaseType": "4",
				"weaponType": "shaman",
				"itemType": "Character",
				"name": "停云"
			},
			{
				"itemId": 1206,
				"damageType": "1",
				"element": "physical",
				"imageUrl": "/darkmatter/hkrpg/prod_gf_cn/item_icon_u642mb/6f8deffb935e0baa68463ad6d6ecab9f.png",
				"rankType": 4,
				"avatarBaseType": "2",
				"weaponType": "rogue",
				"itemType": "Character",
				"name": "素裳"
			},
			{
				"itemId": 1001,
				"damageType": "4",
				"element": "ice",
				"imageUrl": "/darkmatter/hkrpg/prod_gf_cn/item_icon_u642mb/77cdb978c7b10728bf4aa1e4e895be34.png",
				"rankType": 4,
				"avatarBaseType": "6",
				"weaponType": "knight",
				"itemType": "Character",
				"name": "三月七"
			}
		],
		"start": "2023-05-17 18:00:00",
		"end": "2023-06-06 14:59:59"
	},
	{
		"version": "1.0.1",
		"items": [
			{
				"itemId": 1102,
				"damageType": "32",
				"element": "quantum",
				"imageUrl": "/darkmatter/hkrpg/prod_gf_cn/item_icon_u642mb/ca06f18257659c28762f427edfa81c8d.png",
				"rankType": 5,
				"avatarBaseType": "2",
				"weaponType": "rogue",
				"itemType": "Character",
				"name": "希儿"
			},
			{
				"itemId": 1105,
				"damageType": "1",
				"element": "physical",
				"imageUrl": "/darkmatter/hkrpg/prod_gf_cn/item_icon_u642mb/2c02c20be78028dc850682fe67ed5a2d.png",
				"rankType": 4,
				"avatarBaseType": "7",
				"weaponType": "priest",
				"itemType": "Character",
				"name": "娜塔莎"
			},
			{
				"itemId": 1109,
				"damageType": "2",
				"element": "fire",
				"imageUrl": "/darkmatter/hkrpg/prod_gf_cn/item_icon_u642mb/2768214036f435a3204cbde150082a0d.png",
				"rankType": 4,
				"avatarBaseType": "1",
				"weaponType": "warrior",
				"itemType": "Character",
				"name": "虎克"
			},
			{
				"itemId": 1106,
				"damageType": "4",
				"element": "ice",
				"imageUrl": "/darkmatter/hkrpg/prod_gf_cn/item_icon_u642mb/0b49824fcc632e03f73c924fcf5cd313.png",
				"rankType": 4,
				"avatarBaseType": "5",
				"weaponType": "warlock",
				"itemType": "Character",
				"name": "佩拉"
			}
		],
		"start": "2023-04-26 06:00:00",
		"end": "2023-05-17 17:59:59"
	}
]