[
	{
		"version": "2.7.2",
		"items": [
			{
				"itemId": 2494,
				"imageUrl": "/hsr/UI/avatarshopicon/1310.webp",
				"itemType": "Character",
				"name": "流萤",
				"nameEn": "Firefly ",
				"damageType": "fire",
				"element": "fire",
				"rankType": 5,
				"avatarBaseType": "destruction",
				"weaponType": "warrior"
			},
			{
				"itemId": 1924,
				"imageUrl": "/hsr/UI/avatarshopicon/1301.webp",
				"itemType": "Character",
				"name": "加拉赫",
				"nameEn": "Gallagher",
				"damageType": "fire",
				"element": "fire",
				"rankType": 4,
				"avatarBaseType": "abundance",
				"weaponType": "priest"
			},
			{
				"itemId": 712,
				"imageUrl": "/hsr/UI/avatarshopicon/1207.webp",
				"itemType": "Character",
				"name": "驭空",
				"nameEn": "Yukong",
				"damageType": "imaginary",
				"element": "imaginary",
				"rankType": 4,
				"avatarBaseType": "harmony",
				"weaponType": "shaman"
			},
			{
				"itemId": 1808,
				"imageUrl": "/hsr/UI/avatarshopicon/1312.webp",
				"itemType": "Character",
				"name": "米沙",
				"nameEn": "Misha",
				"damageType": "ice",
				"element": "ice",
				"rankType": 4,
				"avatarBaseType": "destruction",
				"weaponType": "warrior"
			}
		],
		"start": "2024-12-25 12:00:00",
		"end": "2025-01-14 14:59:59"
	},
	{
		"version": "2.7.1",
		"items": [
			{
				"itemId": 3150,
				"imageUrl": "/hsr/UI/avatarshopicon/1313.webp",
				"itemType": "Character",
				"name": "星期日",
				"nameEn": "Sunday (Coming Soon)",
				"damageType": "imaginary",
				"element": "imaginary",
				"rankType": 5,
				"avatarBaseType": "harmony",
				"weaponType": "shaman"
			},
			{
				"itemId": 26,
				"imageUrl": "/hsr/UI/avatarshopicon/1204.webp",
				"itemType": "Character",
				"name": "景元",
				"nameEn": "Jing Yuan",
				"damageType": "lightning",
				"element": "thunder",
				"rankType": 5,
				"avatarBaseType": "erudition",
				"weaponType": "mage"
			},
			{
				"itemId": 24,
				"imageUrl": "/hsr/UI/avatarshopicon/1201.webp",
				"itemType": "Character",
				"name": "青雀",
				"nameEn": "Qingque",
				"damageType": "quantum",
				"element": "quantum",
				"rankType": 4,
				"avatarBaseType": "erudition",
				"weaponType": "mage"
			},
			{
				"itemId": 11,
				"imageUrl": "/hsr/UI/avatarshopicon/1008.webp",
				"itemType": "Character",
				"name": "阿兰",
				"nameEn": "Arlan",
				"damageType": "lightning",
				"element": "thunder",
				"rankType": 4,
				"avatarBaseType": "destruction",
				"weaponType": "warrior"
			},
			{
				"itemId": 25,
				"imageUrl": "/hsr/UI/avatarshopicon/1202.webp",
				"itemType": "Character",
				"name": "停云",
				"nameEn": "Tingyun",
				"damageType": "lightning",
				"element": "thunder",
				"rankType": 4,
				"avatarBaseType": "harmony",
				"weaponType": "shaman"
			}
		],
		"start": "2024-12-04 06:00:00",
		"end": "2024-12-25 11:59:59"
	},
	{
		"version": "2.6.2",
		"items": [
			{
				"itemId": 1919,
				"imageUrl": "/hsr/UI/avatarshopicon/1308.webp",
				"itemType": "Character",
				"name": "黄泉",
				"nameEn": "Acheron",
				"damageType": "lightning",
				"element": "thunder",
				"rankType": 5,
				"avatarBaseType": "nihility",
				"weaponType": "warlock"
			},
			{
				"itemId": 1920,
				"imageUrl": "/hsr/UI/avatarshopicon/1304.webp",
				"itemType": "Character",
				"name": "砂金",
				"nameEn": "Aventurine",
				"damageType": "imaginary",
				"element": "imaginary",
				"rankType": 5,
				"avatarBaseType": "preservation",
				"weaponType": "knight"
			},
			{
				"itemId": 7,
				"imageUrl": "/hsr/UI/avatarshopicon/1224.webp",
				"itemType": "Character",
				"name": "三月七 - 存护",
				"nameEn": "March 7th",
				"damageType": "ice",
				"element": "ice",
				"rankType": 4,
				"avatarBaseType": "preservation",
				"weaponType": "knight"
			},
			{
				"itemId": 19,
				"imageUrl": "/hsr/UI/avatarshopicon/1106.webp",
				"itemType": "Character",
				"name": "佩拉",
				"nameEn": "Pela",
				"damageType": "ice",
				"element": "ice",
				"rankType": 4,
				"avatarBaseType": "nihility",
				"weaponType": "warlock"
			},
			{
				"itemId": 21,
				"imageUrl": "/hsr/UI/avatarshopicon/1108.webp",
				"itemType": "Character",
				"name": "桑博",
				"nameEn": "Sampo",
				"damageType": "wind",
				"element": "wind",
				"rankType": 4,
				"avatarBaseType": "nihility",
				"weaponType": "warlock"
			}
		],
		"start": "2024-11-13 12:00:00",
		"end": "2024-12-03 14:59:59"
	},
	{
		"version": "2.6.1",
		"items": [
			{
				"itemId": 3057,
				"imageUrl": "/hsr/UI/avatarshopicon/1317.webp",
				"itemType": "Character",
				"name": "乱破",
				"nameEn": "Rappa",
				"damageType": "imaginary",
				"element": "imaginary",
				"rankType": 5,
				"avatarBaseType": "erudition",
				"weaponType": "mage"
			},
			{
				"itemId": 1226,
				"imageUrl": "/hsr/UI/avatarshopicon/1213.webp",
				"itemType": "Character",
				"name": "丹恒•饮月",
				"nameEn": "Dan Heng • Imbibitor Lunae ",
				"damageType": "imaginary",
				"element": "imaginary",
				"rankType": 5,
				"avatarBaseType": "destruction",
				"weaponType": "warrior"
			},
			{
				"itemId": 1228,
				"imageUrl": "/hsr/UI/avatarshopicon/1110.webp",
				"itemType": "Character",
				"name": "玲可",
				"nameEn": "Lynx",
				"damageType": "quantum",
				"element": "quantum",
				"rankType": 4,
				"avatarBaseType": "abundance",
				"weaponType": "priest"
			},
			{
				"itemId": 1640,
				"imageUrl": "/hsr/UI/avatarshopicon/1214.webp",
				"itemType": "Character",
				"name": "雪衣",
				"nameEn": "Xueyi",
				"damageType": "quantum",
				"element": "quantum",
				"rankType": 4,
				"avatarBaseType": "destruction",
				"weaponType": "warrior"
			},
			{
				"itemId": 712,
				"imageUrl": "/hsr/UI/avatarshopicon/1207.webp",
				"itemType": "Character",
				"name": "驭空",
				"nameEn": "Yukong",
				"damageType": "imaginary",
				"element": "imaginary",
				"rankType": 4,
				"avatarBaseType": "harmony",
				"weaponType": "shaman"
			}
		],
		"start": "2024-10-23 06:00:00",
		"end": "2024-11-13 11:59:59"
	},
	{
		"version": "2.5.2",
		"items": [
			{
				"itemId": 2948,
				"imageUrl": "/hsr/UI/avatarshopicon/1222.webp",
				"itemType": "Character",
				"name": "灵砂",
				"nameEn": "Lingsha",
				"damageType": "fire",
				"element": "fire",
				"rankType": 5,
				"avatarBaseType": "abundance",
				"weaponType": "priest"
			},
			{
				"itemId": 1389,
				"imageUrl": "/hsr/UI/avatarshopicon/1112.webp",
				"itemType": "Character",
				"name": "托帕&账账",
				"nameEn": "Topaz & Numby ",
				"damageType": "fire",
				"element": "fire",
				"rankType": 5,
				"avatarBaseType": "hunt",
				"weaponType": "rogue"
			},
			{
				"itemId": 1808,
				"imageUrl": "/hsr/UI/avatarshopicon/1312.webp",
				"itemType": "Character",
				"name": "米沙",
				"nameEn": "Misha",
				"damageType": "ice",
				"element": "ice",
				"rankType": 4,
				"avatarBaseType": "destruction",
				"weaponType": "warrior"
			},
			{
				"itemId": 18,
				"imageUrl": "/hsr/UI/avatarshopicon/1105.webp",
				"itemType": "Character",
				"name": "娜塔莎",
				"nameEn": "Natasha",
				"damageType": "physical",
				"element": "physical",
				"rankType": 4,
				"avatarBaseType": "abundance",
				"weaponType": "priest"
			},
			{
				"itemId": 1392,
				"imageUrl": "/hsr/UI/avatarshopicon/1210.webp",
				"itemType": "Character",
				"name": "桂乃芬",
				"nameEn": "Guinaifen ",
				"damageType": "fire",
				"element": "fire",
				"rankType": 4,
				"avatarBaseType": "nihility",
				"weaponType": "warlock"
			}
		],
		"start": "2024-10-02 12:00:00",
		"end": "2024-10-22 14:59:59"
	},
	{
		"version": "2.5.1",
		"items": [
			{
				"itemId": 2947,
				"imageUrl": "/hsr/UI/avatarshopicon/1220.webp",
				"itemType": "Character",
				"name": "飞霄",
				"nameEn": "Feixiao",
				"damageType": "wind",
				"element": "wind",
				"rankType": 5,
				"avatarBaseType": "hunt",
				"weaponType": "rogue"
			},
			{
				"itemId": 791,
				"imageUrl": "/hsr/UI/avatarshopicon/1005.webp",
				"itemType": "Character",
				"name": "卡芙卡",
				"nameEn": "Kafka ",
				"damageType": "lightning",
				"element": "thunder",
				"rankType": 5,
				"avatarBaseType": "nihility",
				"weaponType": "warlock"
			},
			{
				"itemId": 1806,
				"imageUrl": "/hsr/UI/avatarshopicon/1307.webp",
				"itemType": "Character",
				"name": "黑天鹅",
				"nameEn": "Black Swan",
				"damageType": "wind",
				"element": "wind",
				"rankType": 5,
				"avatarBaseType": "nihility",
				"weaponType": "warlock"
			},
			{
				"itemId": 2366,
				"imageUrl": "/hsr/UI/avatarshopicon/1309.webp",
				"itemType": "Character",
				"name": "知更鸟",
				"nameEn": "Robin",
				"damageType": "physical",
				"element": "physical",
				"rankType": 5,
				"avatarBaseType": "harmony",
				"weaponType": "shaman"
			},
			{
				"itemId": 2949,
				"imageUrl": "/hsr/UI/avatarshopicon/1223.webp",
				"itemType": "Character",
				"name": "貊泽",
				"nameEn": "Moze",
				"damageType": "lightning",
				"element": "thunder",
				"rankType": 4,
				"avatarBaseType": "hunt",
				"weaponType": "rogue"
			},
			{
				"itemId": 12,
				"imageUrl": "/hsr/UI/avatarshopicon/1009.webp",
				"itemType": "Character",
				"name": "艾丝妲",
				"nameEn": "Asta",
				"damageType": "fire",
				"element": "fire",
				"rankType": 4,
				"avatarBaseType": "harmony",
				"weaponType": "shaman"
			},
			{
				"itemId": 801,
				"imageUrl": "/hsr/UI/avatarshopicon/1111.webp",
				"itemType": "Character",
				"name": "卢卡",
				"nameEn": "Luka",
				"damageType": "physical",
				"element": "physical",
				"rankType": 4,
				"avatarBaseType": "nihility",
				"weaponType": "warlock"
			}
		],
		"start": "2024-09-10 06:00:00",
		"end": "2024-10-02 11:59:59"
	},
	{
		"version": "2.4.2",
		"items": [
			{
				"itemId": 2643,
				"imageUrl": "/hsr/UI/avatarshopicon/1218.webp",
				"itemType": "Character",
				"name": "椒丘",
				"nameEn": "Jiaoqiu",
				"damageType": "fire",
				"element": "fire",
				"rankType": 5,
				"avatarBaseType": "nihility",
				"weaponType": "warlock"
			},
			{
				"itemId": 1807,
				"imageUrl": "/hsr/UI/avatarshopicon/1306.webp",
				"itemType": "Character",
				"name": "花火",
				"nameEn": "Sparkle",
				"damageType": "quantum",
				"element": "quantum",
				"rankType": 5,
				"avatarBaseType": "harmony",
				"weaponType": "shaman"
			},
			{
				"itemId": 22,
				"imageUrl": "/hsr/UI/avatarshopicon/1109.webp",
				"itemType": "Character",
				"name": "虎克",
				"nameEn": "Hook",
				"damageType": "fire",
				"element": "fire",
				"rankType": 4,
				"avatarBaseType": "destruction",
				"weaponType": "warrior"
			},
			{
				"itemId": 1392,
				"imageUrl": "/hsr/UI/avatarshopicon/1210.webp",
				"itemType": "Character",
				"name": "桂乃芬",
				"nameEn": "Guinaifen ",
				"damageType": "fire",
				"element": "fire",
				"rankType": 4,
				"avatarBaseType": "nihility",
				"weaponType": "warlock"
			},
			{
				"itemId": 11,
				"imageUrl": "/hsr/UI/avatarshopicon/1008.webp",
				"itemType": "Character",
				"name": "阿兰",
				"nameEn": "Arlan",
				"damageType": "lightning",
				"element": "thunder",
				"rankType": 4,
				"avatarBaseType": "destruction",
				"weaponType": "warrior"
			}
		],
		"start": "2024-08-21 12:00:00",
		"end": "2024-09-09 14:59:59"
	},
	{
		"version": "2.4.1",
		"items": [
			{
				"itemId": 2642,
				"imageUrl": "/hsr/UI/avatarshopicon/1221.webp",
				"itemType": "Character",
				"name": "云璃",
				"nameEn": "Yunli",
				"damageType": "physical",
				"element": "physical",
				"rankType": 5,
				"avatarBaseType": "destruction",
				"weaponType": "warrior"
			},
			{
				"itemId": 1533,
				"imageUrl": "/hsr/UI/avatarshopicon/1217.webp",
				"itemType": "Character",
				"name": "藿藿",
				"nameEn": "Huohuo ",
				"damageType": "wind",
				"element": "wind",
				"rankType": 5,
				"avatarBaseType": "abundance",
				"weaponType": "priest"
			},
			{
				"itemId": 1537,
				"imageUrl": "/hsr/UI/avatarshopicon/1215.webp",
				"itemType": "Character",
				"name": "寒鸦",
				"nameEn": "Hanya",
				"damageType": "physical",
				"element": "physical",
				"rankType": 4,
				"avatarBaseType": "harmony",
				"weaponType": "shaman"
			},
			{
				"itemId": 712,
				"imageUrl": "/hsr/UI/avatarshopicon/1207.webp",
				"itemType": "Character",
				"name": "驭空",
				"nameEn": "Yukong",
				"damageType": "imaginary",
				"element": "imaginary",
				"rankType": 4,
				"avatarBaseType": "harmony",
				"weaponType": "shaman"
			},
			{
				"itemId": 1228,
				"imageUrl": "/hsr/UI/avatarshopicon/1110.webp",
				"itemType": "Character",
				"name": "玲可",
				"nameEn": "Lynx",
				"damageType": "quantum",
				"element": "quantum",
				"rankType": 4,
				"avatarBaseType": "abundance",
				"weaponType": "priest"
			}
		],
		"start": "2024-07-31 06:00:00",
		"end": "2024-08-21 11:59:59"
	},
	{
		"version": "2.3.2",
		"items": [
			{
				"itemId": 2495,
				"imageUrl": "/hsr/UI/avatarshopicon/1314.webp",
				"itemType": "Character",
				"name": "翡翠",
				"nameEn": "Jade",
				"damageType": "quantum",
				"element": "quantum",
				"rankType": 5,
				"avatarBaseType": "erudition",
				"weaponType": "mage"
			},
			{
				"itemId": 1535,
				"imageUrl": "/hsr/UI/avatarshopicon/1302.webp",
				"itemType": "Character",
				"name": "银枝",
				"nameEn": "Argenti",
				"damageType": "physical",
				"element": "physical",
				"rankType": 5,
				"avatarBaseType": "erudition",
				"weaponType": "mage"
			},
			{
				"itemId": 16,
				"imageUrl": "/hsr/UI/avatarshopicon/1103.webp",
				"itemType": "Character",
				"name": "希露瓦",
				"nameEn": "Serval",
				"damageType": "lightning",
				"element": "thunder",
				"rankType": 4,
				"avatarBaseType": "erudition",
				"weaponType": "mage"
			},
			{
				"itemId": 18,
				"imageUrl": "/hsr/UI/avatarshopicon/1105.webp",
				"itemType": "Character",
				"name": "娜塔莎",
				"nameEn": "Natasha",
				"damageType": "physical",
				"element": "physical",
				"rankType": 4,
				"avatarBaseType": "abundance",
				"weaponType": "priest"
			},
			{
				"itemId": 12,
				"imageUrl": "/hsr/UI/avatarshopicon/1009.webp",
				"itemType": "Character",
				"name": "艾丝妲",
				"nameEn": "Asta",
				"damageType": "fire",
				"element": "fire",
				"rankType": 4,
				"avatarBaseType": "harmony",
				"weaponType": "shaman"
			}
		],
		"start": "2024-07-10 12:00:00",
		"end": "2024-07-30 14:59:59"
	},
	{
		"version": "2.3.1",
		"items": [
			{
				"itemId": 2494,
				"imageUrl": "/hsr/UI/avatarshopicon/1310.webp",
				"itemType": "Character",
				"name": "流萤",
				"nameEn": "Firefly ",
				"damageType": "fire",
				"element": "fire",
				"rankType": 5,
				"avatarBaseType": "destruction",
				"weaponType": "warrior"
			},
			{
				"itemId": 1638,
				"imageUrl": "/hsr/UI/avatarshopicon/1303.webp",
				"itemType": "Character",
				"name": "阮•梅",
				"nameEn": "Ruan Mei",
				"damageType": "ice",
				"element": "ice",
				"rankType": 5,
				"avatarBaseType": "harmony",
				"weaponType": "shaman"
			},
			{
				"itemId": 1924,
				"imageUrl": "/hsr/UI/avatarshopicon/1301.webp",
				"itemType": "Character",
				"name": "加拉赫",
				"nameEn": "Gallagher",
				"damageType": "fire",
				"element": "fire",
				"rankType": 4,
				"avatarBaseType": "abundance",
				"weaponType": "priest"
			},
			{
				"itemId": 1808,
				"imageUrl": "/hsr/UI/avatarshopicon/1312.webp",
				"itemType": "Character",
				"name": "米沙",
				"nameEn": "Misha",
				"damageType": "ice",
				"element": "ice",
				"rankType": 4,
				"avatarBaseType": "destruction",
				"weaponType": "warrior"
			},
			{
				"itemId": 1640,
				"imageUrl": "/hsr/UI/avatarshopicon/1214.webp",
				"itemType": "Character",
				"name": "雪衣",
				"nameEn": "Xueyi",
				"damageType": "quantum",
				"element": "quantum",
				"rankType": 4,
				"avatarBaseType": "destruction",
				"weaponType": "warrior"
			}
		],
		"start": "2024-06-19 06:00:00",
		"end": "2024-07-10 11:59:59"
	},
	{
		"version": "2.2.2",
		"items": [
			{
				"itemId": 2367,
				"imageUrl": "/hsr/UI/avatarshopicon/1315.webp",
				"itemType": "Character",
				"name": "波提欧",
				"nameEn": "Boothill",
				"damageType": "physical",
				"element": "physical",
				"rankType": 5,
				"avatarBaseType": "hunt",
				"weaponType": "rogue"
			},
			{
				"itemId": 804,
				"imageUrl": "/hsr/UI/avatarshopicon/1208.webp",
				"itemType": "Character",
				"name": "符玄",
				"nameEn": "Fu Xuan",
				"damageType": "quantum",
				"element": "quantum",
				"rankType": 5,
				"avatarBaseType": "preservation",
				"weaponType": "knight"
			},
			{
				"itemId": 19,
				"imageUrl": "/hsr/UI/avatarshopicon/1106.webp",
				"itemType": "Character",
				"name": "佩拉",
				"nameEn": "Pela",
				"damageType": "ice",
				"element": "ice",
				"rankType": 4,
				"avatarBaseType": "nihility",
				"weaponType": "warlock"
			},
			{
				"itemId": 801,
				"imageUrl": "/hsr/UI/avatarshopicon/1111.webp",
				"itemType": "Character",
				"name": "卢卡",
				"nameEn": "Luka",
				"damageType": "physical",
				"element": "physical",
				"rankType": 4,
				"avatarBaseType": "nihility",
				"weaponType": "warlock"
			},
			{
				"itemId": 22,
				"imageUrl": "/hsr/UI/avatarshopicon/1109.webp",
				"itemType": "Character",
				"name": "虎克",
				"nameEn": "Hook",
				"damageType": "fire",
				"element": "fire",
				"rankType": 4,
				"avatarBaseType": "destruction",
				"weaponType": "warrior"
			}
		],
		"start": "2024-05-29 12:00:00",
		"end": "2024-06-18 14:59:59"
	},
	{
		"version": "2.2.1",
		"items": [
			{
				"itemId": 2366,
				"imageUrl": "/hsr/UI/avatarshopicon/1309.webp",
				"itemType": "Character",
				"name": "知更鸟",
				"nameEn": "Robin",
				"damageType": "physical",
				"element": "physical",
				"rankType": 5,
				"avatarBaseType": "harmony",
				"weaponType": "shaman"
			},
			{
				"itemId": 1389,
				"imageUrl": "/hsr/UI/avatarshopicon/1112.webp",
				"itemType": "Character",
				"name": "托帕&账账",
				"nameEn": "Topaz & Numby ",
				"damageType": "fire",
				"element": "fire",
				"rankType": 5,
				"avatarBaseType": "hunt",
				"weaponType": "rogue"
			},
			{
				"itemId": 7,
				"imageUrl": "/hsr/UI/avatarshopicon/1224.webp",
				"itemType": "Character",
				"name": "三月七 - 存护",
				"nameEn": "March 7th",
				"damageType": "ice",
				"element": "ice",
				"rankType": 4,
				"avatarBaseType": "preservation",
				"weaponType": "knight"
			},
			{
				"itemId": 1537,
				"imageUrl": "/hsr/UI/avatarshopicon/1215.webp",
				"itemType": "Character",
				"name": "寒鸦",
				"nameEn": "Hanya",
				"damageType": "physical",
				"element": "physical",
				"rankType": 4,
				"avatarBaseType": "harmony",
				"weaponType": "shaman"
			},
			{
				"itemId": 1640,
				"imageUrl": "/hsr/UI/avatarshopicon/1214.webp",
				"itemType": "Character",
				"name": "雪衣",
				"nameEn": "Xueyi",
				"damageType": "quantum",
				"element": "quantum",
				"rankType": 4,
				"avatarBaseType": "destruction",
				"weaponType": "warrior"
			}
		],
		"start": "2024-05-08 06:00:00",
		"end": "2024-05-29 11:59:59"
	},
	{
		"version": "2.1.2",
		"items": [
			{
				"itemId": 1920,
				"imageUrl": "/hsr/UI/avatarshopicon/1304.webp",
				"itemType": "Character",
				"name": "砂金",
				"nameEn": "Aventurine",
				"damageType": "imaginary",
				"element": "imaginary",
				"rankType": 5,
				"avatarBaseType": "preservation",
				"weaponType": "knight"
			},
			{
				"itemId": 1387,
				"imageUrl": "/hsr/UI/avatarshopicon/1212.webp",
				"itemType": "Character",
				"name": "镜流",
				"nameEn": "Jingliu ",
				"damageType": "ice",
				"element": "ice",
				"rankType": 5,
				"avatarBaseType": "destruction",
				"weaponType": "warrior"
			},
			{
				"itemId": 1228,
				"imageUrl": "/hsr/UI/avatarshopicon/1110.webp",
				"itemType": "Character",
				"name": "玲可",
				"nameEn": "Lynx",
				"damageType": "quantum",
				"element": "quantum",
				"rankType": 4,
				"avatarBaseType": "abundance",
				"weaponType": "priest"
			},
			{
				"itemId": 801,
				"imageUrl": "/hsr/UI/avatarshopicon/1111.webp",
				"itemType": "Character",
				"name": "卢卡",
				"nameEn": "Luka",
				"damageType": "physical",
				"element": "physical",
				"rankType": 4,
				"avatarBaseType": "nihility",
				"weaponType": "warlock"
			},
			{
				"itemId": 16,
				"imageUrl": "/hsr/UI/avatarshopicon/1103.webp",
				"itemType": "Character",
				"name": "希露瓦",
				"nameEn": "Serval",
				"damageType": "lightning",
				"element": "thunder",
				"rankType": 4,
				"avatarBaseType": "erudition",
				"weaponType": "mage"
			}
		],
		"start": "2024-04-17 12:00:00",
		"end": "2024-05-07 14:59:59"
	},
	{
		"version": "2.1.1",
		"items": [
			{
				"itemId": 1919,
				"imageUrl": "/hsr/UI/avatarshopicon/1308.webp",
				"itemType": "Character",
				"name": "黄泉",
				"nameEn": "Acheron",
				"damageType": "lightning",
				"element": "thunder",
				"rankType": 5,
				"avatarBaseType": "nihility",
				"weaponType": "warlock"
			},
			{
				"itemId": 711,
				"imageUrl": "/hsr/UI/avatarshopicon/1203.webp",
				"itemType": "Character",
				"name": "罗刹",
				"nameEn": "Luocha",
				"damageType": "imaginary",
				"element": "imaginary",
				"rankType": 5,
				"avatarBaseType": "abundance",
				"weaponType": "priest"
			},
			{
				"itemId": 1924,
				"imageUrl": "/hsr/UI/avatarshopicon/1301.webp",
				"itemType": "Character",
				"name": "加拉赫",
				"nameEn": "Gallagher",
				"damageType": "fire",
				"element": "fire",
				"rankType": 4,
				"avatarBaseType": "abundance",
				"weaponType": "priest"
			},
			{
				"itemId": 19,
				"imageUrl": "/hsr/UI/avatarshopicon/1106.webp",
				"itemType": "Character",
				"name": "佩拉",
				"nameEn": "Pela",
				"damageType": "ice",
				"element": "ice",
				"rankType": 4,
				"avatarBaseType": "nihility",
				"weaponType": "warlock"
			},
			{
				"itemId": 8,
				"imageUrl": "/hsr/UI/avatarshopicon/1002.webp",
				"itemType": "Character",
				"name": "丹恒",
				"nameEn": "Dan Heng",
				"damageType": "wind",
				"element": "wind",
				"rankType": 4,
				"avatarBaseType": "hunt",
				"weaponType": "rogue"
			}
		],
		"start": "2024-03-27 06:00:00",
		"end": "2024-04-17 11:59:59"
	},
	{
		"version": "2.0.2",
		"items": [
			{
				"itemId": 1807,
				"imageUrl": "/hsr/UI/avatarshopicon/1306.webp",
				"itemType": "Character",
				"name": "花火",
				"nameEn": "Sparkle",
				"damageType": "quantum",
				"element": "quantum",
				"rankType": 5,
				"avatarBaseType": "harmony",
				"weaponType": "shaman"
			},
			{
				"itemId": 26,
				"imageUrl": "/hsr/UI/avatarshopicon/1204.webp",
				"itemType": "Character",
				"name": "景元",
				"nameEn": "Jing Yuan",
				"damageType": "lightning",
				"element": "thunder",
				"rankType": 5,
				"avatarBaseType": "erudition",
				"weaponType": "mage"
			},
			{
				"itemId": 21,
				"imageUrl": "/hsr/UI/avatarshopicon/1108.webp",
				"itemType": "Character",
				"name": "桑博",
				"nameEn": "Sampo",
				"damageType": "wind",
				"element": "wind",
				"rankType": 4,
				"avatarBaseType": "nihility",
				"weaponType": "warlock"
			},
			{
				"itemId": 24,
				"imageUrl": "/hsr/UI/avatarshopicon/1201.webp",
				"itemType": "Character",
				"name": "青雀",
				"nameEn": "Qingque",
				"damageType": "quantum",
				"element": "quantum",
				"rankType": 4,
				"avatarBaseType": "erudition",
				"weaponType": "mage"
			},
			{
				"itemId": 1537,
				"imageUrl": "/hsr/UI/avatarshopicon/1215.webp",
				"itemType": "Character",
				"name": "寒鸦",
				"nameEn": "Hanya",
				"damageType": "physical",
				"element": "physical",
				"rankType": 4,
				"avatarBaseType": "harmony",
				"weaponType": "shaman"
			}
		],
		"start": "2024-02-29 12:00:00",
		"end": "2024-03-26 14:59:59"
	},
	{
		"version": "2.0.1",
		"items": [
			{
				"itemId": 1806,
				"imageUrl": "/hsr/UI/avatarshopicon/1307.webp",
				"itemType": "Character",
				"name": "黑天鹅",
				"nameEn": "Black Swan",
				"damageType": "wind",
				"element": "wind",
				"rankType": 5,
				"avatarBaseType": "nihility",
				"weaponType": "warlock"
			},
			{
				"itemId": 1226,
				"imageUrl": "/hsr/UI/avatarshopicon/1213.webp",
				"itemType": "Character",
				"name": "丹恒•饮月",
				"nameEn": "Dan Heng • Imbibitor Lunae ",
				"damageType": "imaginary",
				"element": "imaginary",
				"rankType": 5,
				"avatarBaseType": "destruction",
				"weaponType": "warrior"
			},
			{
				"itemId": 1808,
				"imageUrl": "/hsr/UI/avatarshopicon/1312.webp",
				"itemType": "Character",
				"name": "米沙",
				"nameEn": "Misha",
				"damageType": "ice",
				"element": "ice",
				"rankType": 4,
				"avatarBaseType": "destruction",
				"weaponType": "warrior"
			},
			{
				"itemId": 25,
				"imageUrl": "/hsr/UI/avatarshopicon/1202.webp",
				"itemType": "Character",
				"name": "停云",
				"nameEn": "Tingyun",
				"damageType": "lightning",
				"element": "thunder",
				"rankType": 4,
				"avatarBaseType": "harmony",
				"weaponType": "shaman"
			},
			{
				"itemId": 1392,
				"imageUrl": "/hsr/UI/avatarshopicon/1210.webp",
				"itemType": "Character",
				"name": "桂乃芬",
				"nameEn": "Guinaifen ",
				"damageType": "fire",
				"element": "fire",
				"rankType": 4,
				"avatarBaseType": "nihility",
				"weaponType": "warlock"
			}
		],
		"start": "2024-02-06 06:00:00",
		"end": "2024-02-29 11:59:59"
	},
	{
		"version": "1.6.2",
		"items": [
			{
				"itemId": 1639,
				"imageUrl": "/hsr/UI/avatarshopicon/1305.webp",
				"itemType": "Character",
				"name": "真理医生",
				"nameEn": "Dr. Ratio",
				"damageType": "imaginary",
				"element": "imaginary",
				"rankType": 5,
				"avatarBaseType": "hunt",
				"weaponType": "rogue"
			},
			{
				"itemId": 791,
				"imageUrl": "/hsr/UI/avatarshopicon/1005.webp",
				"itemType": "Character",
				"name": "卡芙卡",
				"nameEn": "Kafka ",
				"damageType": "lightning",
				"element": "thunder",
				"rankType": 5,
				"avatarBaseType": "nihility",
				"weaponType": "warlock"
			},
			{
				"itemId": 27,
				"imageUrl": "/hsr/UI/avatarshopicon/1206.webp",
				"itemType": "Character",
				"name": "素裳",
				"nameEn": "Sushang",
				"damageType": "physical",
				"element": "physical",
				"rankType": 4,
				"avatarBaseType": "hunt",
				"weaponType": "rogue"
			},
			{
				"itemId": 18,
				"imageUrl": "/hsr/UI/avatarshopicon/1105.webp",
				"itemType": "Character",
				"name": "娜塔莎",
				"nameEn": "Natasha",
				"damageType": "physical",
				"element": "physical",
				"rankType": 4,
				"avatarBaseType": "abundance",
				"weaponType": "priest"
			},
			{
				"itemId": 22,
				"imageUrl": "/hsr/UI/avatarshopicon/1109.webp",
				"itemType": "Character",
				"name": "虎克",
				"nameEn": "Hook",
				"damageType": "fire",
				"element": "fire",
				"rankType": 4,
				"avatarBaseType": "destruction",
				"weaponType": "warrior"
			}
		],
		"start": "2024-01-17 12:00:00",
		"end": "2024-02-05 14:59:59"
	},
	{
		"version": "1.6.1",
		"items": [
			{
				"itemId": 1638,
				"imageUrl": "/hsr/UI/avatarshopicon/1303.webp",
				"itemType": "Character",
				"name": "阮•梅",
				"nameEn": "Ruan Mei",
				"damageType": "ice",
				"element": "ice",
				"rankType": 5,
				"avatarBaseType": "harmony",
				"weaponType": "shaman"
			},
			{
				"itemId": 789,
				"imageUrl": "/hsr/UI/avatarshopicon/1205.webp",
				"itemType": "Character",
				"name": "刃",
				"nameEn": "Blade",
				"damageType": "wind",
				"element": "wind",
				"rankType": 5,
				"avatarBaseType": "destruction",
				"weaponType": "warrior"
			},
			{
				"itemId": 1640,
				"imageUrl": "/hsr/UI/avatarshopicon/1214.webp",
				"itemType": "Character",
				"name": "雪衣",
				"nameEn": "Xueyi",
				"damageType": "quantum",
				"element": "quantum",
				"rankType": 4,
				"avatarBaseType": "destruction",
				"weaponType": "warrior"
			},
			{
				"itemId": 7,
				"imageUrl": "/hsr/UI/avatarshopicon/1224.webp",
				"itemType": "Character",
				"name": "三月七 - 存护",
				"nameEn": "March 7th",
				"damageType": "ice",
				"element": "ice",
				"rankType": 4,
				"avatarBaseType": "preservation",
				"weaponType": "knight"
			},
			{
				"itemId": 25,
				"imageUrl": "/hsr/UI/avatarshopicon/1202.webp",
				"itemType": "Character",
				"name": "停云",
				"nameEn": "Tingyun",
				"damageType": "lightning",
				"element": "thunder",
				"rankType": 4,
				"avatarBaseType": "harmony",
				"weaponType": "shaman"
			}
		],
		"start": "2023-12-27 06:00:00",
		"end": "2024-01-17 11:59:59"
	},
	{
		"version": "1.5.2",
		"items": [
			{
				"itemId": 1535,
				"imageUrl": "/hsr/UI/avatarshopicon/1302.webp",
				"itemType": "Character",
				"name": "银枝",
				"nameEn": "Argenti",
				"damageType": "physical",
				"element": "physical",
				"rankType": 5,
				"avatarBaseType": "erudition",
				"weaponType": "mage"
			},
			{
				"itemId": 710,
				"imageUrl": "/hsr/UI/avatarshopicon/1006.webp",
				"itemType": "Character",
				"name": "银狼",
				"nameEn": "Silver Wolf",
				"damageType": "quantum",
				"element": "quantum",
				"rankType": 5,
				"avatarBaseType": "nihility",
				"weaponType": "warlock"
			},
			{
				"itemId": 1537,
				"imageUrl": "/hsr/UI/avatarshopicon/1215.webp",
				"itemType": "Character",
				"name": "寒鸦",
				"nameEn": "Hanya",
				"damageType": "physical",
				"element": "physical",
				"rankType": 4,
				"avatarBaseType": "harmony",
				"weaponType": "shaman"
			},
			{
				"itemId": 1228,
				"imageUrl": "/hsr/UI/avatarshopicon/1110.webp",
				"itemType": "Character",
				"name": "玲可",
				"nameEn": "Lynx",
				"damageType": "quantum",
				"element": "quantum",
				"rankType": 4,
				"avatarBaseType": "abundance",
				"weaponType": "priest"
			},
			{
				"itemId": 12,
				"imageUrl": "/hsr/UI/avatarshopicon/1009.webp",
				"itemType": "Character",
				"name": "艾丝妲",
				"nameEn": "Asta",
				"damageType": "fire",
				"element": "fire",
				"rankType": 4,
				"avatarBaseType": "harmony",
				"weaponType": "shaman"
			}
		],
		"start": "2023-12-06 12:00:00",
		"end": "2023-12-26 14:59:59"
	},
	{
		"version": "1.5.1",
		"items": [
			{
				"itemId": 1533,
				"imageUrl": "/hsr/UI/avatarshopicon/1217.webp",
				"itemType": "Character",
				"name": "藿藿",
				"nameEn": "Huohuo ",
				"damageType": "wind",
				"element": "wind",
				"rankType": 5,
				"avatarBaseType": "abundance",
				"weaponType": "priest"
			},
			{
				"itemId": 8,
				"imageUrl": "/hsr/UI/avatarshopicon/1002.webp",
				"itemType": "Character",
				"name": "丹恒",
				"nameEn": "Dan Heng",
				"damageType": "wind",
				"element": "wind",
				"rankType": 4,
				"avatarBaseType": "hunt",
				"weaponType": "rogue"
			},
			{
				"itemId": 11,
				"imageUrl": "/hsr/UI/avatarshopicon/1008.webp",
				"itemType": "Character",
				"name": "阿兰",
				"nameEn": "Arlan",
				"damageType": "lightning",
				"element": "thunder",
				"rankType": 4,
				"avatarBaseType": "destruction",
				"weaponType": "warrior"
			},
			{
				"itemId": 16,
				"imageUrl": "/hsr/UI/avatarshopicon/1103.webp",
				"itemType": "Character",
				"name": "希露瓦",
				"nameEn": "Serval",
				"damageType": "lightning",
				"element": "thunder",
				"rankType": 4,
				"avatarBaseType": "erudition",
				"weaponType": "mage"
			}
		],
		"start": "2023-11-15 06:00:00",
		"end": "2023-12-06 11:59:59"
	},
	{
		"version": "1.4.2",
		"items": [
			{
				"itemId": 1389,
				"imageUrl": "/hsr/UI/avatarshopicon/1112.webp",
				"itemType": "Character",
				"name": "托帕&账账",
				"nameEn": "Topaz & Numby ",
				"damageType": "fire",
				"element": "fire",
				"rankType": 5,
				"avatarBaseType": "hunt",
				"weaponType": "rogue"
			},
			{
				"itemId": 15,
				"imageUrl": "/hsr/UI/avatarshopicon/1102.webp",
				"itemType": "Character",
				"name": "希儿",
				"nameEn": "Seele",
				"damageType": "quantum",
				"element": "quantum",
				"rankType": 5,
				"avatarBaseType": "hunt",
				"weaponType": "rogue"
			},
			{
				"itemId": 1392,
				"imageUrl": "/hsr/UI/avatarshopicon/1210.webp",
				"itemType": "Character",
				"name": "桂乃芬",
				"nameEn": "Guinaifen ",
				"damageType": "fire",
				"element": "fire",
				"rankType": 4,
				"avatarBaseType": "nihility",
				"weaponType": "warlock"
			},
			{
				"itemId": 801,
				"imageUrl": "/hsr/UI/avatarshopicon/1111.webp",
				"itemType": "Character",
				"name": "卢卡",
				"nameEn": "Luka",
				"damageType": "physical",
				"element": "physical",
				"rankType": 4,
				"avatarBaseType": "nihility",
				"weaponType": "warlock"
			},
			{
				"itemId": 27,
				"imageUrl": "/hsr/UI/avatarshopicon/1206.webp",
				"itemType": "Character",
				"name": "素裳",
				"nameEn": "Sushang",
				"damageType": "physical",
				"element": "physical",
				"rankType": 4,
				"avatarBaseType": "hunt",
				"weaponType": "rogue"
			}
		],
		"start": "2023-10-27 12:00:00",
		"end": "2023-11-14 14:59:59"
	},
	{
		"version": "1.4.1",
		"items": [
			{
				"itemId": 1387,
				"imageUrl": "/hsr/UI/avatarshopicon/1212.webp",
				"itemType": "Character",
				"name": "镜流",
				"nameEn": "Jingliu ",
				"damageType": "ice",
				"element": "ice",
				"rankType": 5,
				"avatarBaseType": "destruction",
				"weaponType": "warrior"
			},
			{
				"itemId": 25,
				"imageUrl": "/hsr/UI/avatarshopicon/1202.webp",
				"itemType": "Character",
				"name": "停云",
				"nameEn": "Tingyun",
				"damageType": "lightning",
				"element": "thunder",
				"rankType": 4,
				"avatarBaseType": "harmony",
				"weaponType": "shaman"
			},
			{
				"itemId": 24,
				"imageUrl": "/hsr/UI/avatarshopicon/1201.webp",
				"itemType": "Character",
				"name": "青雀",
				"nameEn": "Qingque",
				"damageType": "quantum",
				"element": "quantum",
				"rankType": 4,
				"avatarBaseType": "erudition",
				"weaponType": "mage"
			},
			{
				"itemId": 21,
				"imageUrl": "/hsr/UI/avatarshopicon/1108.webp",
				"itemType": "Character",
				"name": "桑博",
				"nameEn": "Sampo",
				"damageType": "wind",
				"element": "wind",
				"rankType": 4,
				"avatarBaseType": "nihility",
				"weaponType": "warlock"
			}
		],
		"start": "2023-10-11 06:00:00",
		"end": "2023-10-27 11:59:59"
	},
	{
		"version": "1.3.2",
		"items": [
			{
				"itemId": 804,
				"imageUrl": "/hsr/UI/avatarshopicon/1208.webp",
				"itemType": "Character",
				"name": "符玄",
				"nameEn": "Fu Xuan",
				"damageType": "quantum",
				"element": "quantum",
				"rankType": 5,
				"avatarBaseType": "preservation",
				"weaponType": "knight"
			},
			{
				"itemId": 1228,
				"imageUrl": "/hsr/UI/avatarshopicon/1110.webp",
				"itemType": "Character",
				"name": "玲可",
				"nameEn": "Lynx",
				"damageType": "quantum",
				"element": "quantum",
				"rankType": 4,
				"avatarBaseType": "abundance",
				"weaponType": "priest"
			},
			{
				"itemId": 22,
				"imageUrl": "/hsr/UI/avatarshopicon/1109.webp",
				"itemType": "Character",
				"name": "虎克",
				"nameEn": "Hook",
				"damageType": "fire",
				"element": "fire",
				"rankType": 4,
				"avatarBaseType": "destruction",
				"weaponType": "warrior"
			},
			{
				"itemId": 19,
				"imageUrl": "/hsr/UI/avatarshopicon/1106.webp",
				"itemType": "Character",
				"name": "佩拉",
				"nameEn": "Pela",
				"damageType": "ice",
				"element": "ice",
				"rankType": 4,
				"avatarBaseType": "nihility",
				"weaponType": "warlock"
			}
		],
		"start": "2023-09-20 12:00:00",
		"end": "2023-10-10 14:59:59"
	},
	{
		"version": "1.3.1",
		"items": [
			{
				"itemId": 1226,
				"imageUrl": "/hsr/UI/avatarshopicon/1213.webp",
				"itemType": "Character",
				"name": "丹恒•饮月",
				"nameEn": "Dan Heng • Imbibitor Lunae ",
				"damageType": "imaginary",
				"element": "imaginary",
				"rankType": 5,
				"avatarBaseType": "destruction",
				"weaponType": "warrior"
			},
			{
				"itemId": 712,
				"imageUrl": "/hsr/UI/avatarshopicon/1207.webp",
				"itemType": "Character",
				"name": "驭空",
				"nameEn": "Yukong",
				"damageType": "imaginary",
				"element": "imaginary",
				"rankType": 4,
				"avatarBaseType": "harmony",
				"weaponType": "shaman"
			},
			{
				"itemId": 12,
				"imageUrl": "/hsr/UI/avatarshopicon/1009.webp",
				"itemType": "Character",
				"name": "艾丝妲",
				"nameEn": "Asta",
				"damageType": "fire",
				"element": "fire",
				"rankType": 4,
				"avatarBaseType": "harmony",
				"weaponType": "shaman"
			},
			{
				"itemId": 7,
				"imageUrl": "/hsr/UI/avatarshopicon/1224.webp",
				"itemType": "Character",
				"name": "三月七 - 存护",
				"nameEn": "March 7th",
				"damageType": "ice",
				"element": "ice",
				"rankType": 4,
				"avatarBaseType": "preservation",
				"weaponType": "knight"
			}
		],
		"start": "2023-08-30 06:00:00",
		"end": "2023-09-20 11:59:59"
	},
	{
		"version": "1.2.2",
		"items": [
			{
				"itemId": 791,
				"imageUrl": "/hsr/UI/avatarshopicon/1005.webp",
				"itemType": "Character",
				"name": "卡芙卡",
				"nameEn": "Kafka ",
				"damageType": "lightning",
				"element": "thunder",
				"rankType": 5,
				"avatarBaseType": "nihility",
				"weaponType": "warlock"
			},
			{
				"itemId": 801,
				"imageUrl": "/hsr/UI/avatarshopicon/1111.webp",
				"itemType": "Character",
				"name": "卢卡",
				"nameEn": "Luka",
				"damageType": "physical",
				"element": "physical",
				"rankType": 4,
				"avatarBaseType": "nihility",
				"weaponType": "warlock"
			},
			{
				"itemId": 21,
				"imageUrl": "/hsr/UI/avatarshopicon/1108.webp",
				"itemType": "Character",
				"name": "桑博",
				"nameEn": "Sampo",
				"damageType": "wind",
				"element": "wind",
				"rankType": 4,
				"avatarBaseType": "nihility",
				"weaponType": "warlock"
			},
			{
				"itemId": 16,
				"imageUrl": "/hsr/UI/avatarshopicon/1103.webp",
				"itemType": "Character",
				"name": "希露瓦",
				"nameEn": "Serval",
				"damageType": "lightning",
				"element": "thunder",
				"rankType": 4,
				"avatarBaseType": "erudition",
				"weaponType": "mage"
			}
		],
		"start": "2023-08-09 12:00:00",
		"end": "2023-08-29 14:59:59"
	},
	{
		"version": "1.2.1",
		"items": [
			{
				"itemId": 789,
				"imageUrl": "/hsr/UI/avatarshopicon/1205.webp",
				"itemType": "Character",
				"name": "刃",
				"nameEn": "Blade",
				"damageType": "wind",
				"element": "wind",
				"rankType": 5,
				"avatarBaseType": "destruction",
				"weaponType": "warrior"
			},
			{
				"itemId": 11,
				"imageUrl": "/hsr/UI/avatarshopicon/1008.webp",
				"itemType": "Character",
				"name": "阿兰",
				"nameEn": "Arlan",
				"damageType": "lightning",
				"element": "thunder",
				"rankType": 4,
				"avatarBaseType": "destruction",
				"weaponType": "warrior"
			},
			{
				"itemId": 18,
				"imageUrl": "/hsr/UI/avatarshopicon/1105.webp",
				"itemType": "Character",
				"name": "娜塔莎",
				"nameEn": "Natasha",
				"damageType": "physical",
				"element": "physical",
				"rankType": 4,
				"avatarBaseType": "abundance",
				"weaponType": "priest"
			},
			{
				"itemId": 27,
				"imageUrl": "/hsr/UI/avatarshopicon/1206.webp",
				"itemType": "Character",
				"name": "素裳",
				"nameEn": "Sushang",
				"damageType": "physical",
				"element": "physical",
				"rankType": 4,
				"avatarBaseType": "hunt",
				"weaponType": "rogue"
			}
		],
		"start": "2023-07-19 06:00:00",
		"end": "2023-08-09 11:59:59"
	},
	{
		"version": "1.1.2",
		"items": [
			{
				"itemId": 711,
				"imageUrl": "/hsr/UI/avatarshopicon/1203.webp",
				"itemType": "Character",
				"name": "罗刹",
				"nameEn": "Luocha",
				"damageType": "imaginary",
				"element": "imaginary",
				"rankType": 5,
				"avatarBaseType": "abundance",
				"weaponType": "priest"
			},
			{
				"itemId": 712,
				"imageUrl": "/hsr/UI/avatarshopicon/1207.webp",
				"itemType": "Character",
				"name": "驭空",
				"nameEn": "Yukong",
				"damageType": "imaginary",
				"element": "imaginary",
				"rankType": 4,
				"avatarBaseType": "harmony",
				"weaponType": "shaman"
			},
			{
				"itemId": 19,
				"imageUrl": "/hsr/UI/avatarshopicon/1106.webp",
				"itemType": "Character",
				"name": "佩拉",
				"nameEn": "Pela",
				"damageType": "ice",
				"element": "ice",
				"rankType": 4,
				"avatarBaseType": "nihility",
				"weaponType": "warlock"
			},
			{
				"itemId": 24,
				"imageUrl": "/hsr/UI/avatarshopicon/1201.webp",
				"itemType": "Character",
				"name": "青雀",
				"nameEn": "Qingque",
				"damageType": "quantum",
				"element": "quantum",
				"rankType": 4,
				"avatarBaseType": "erudition",
				"weaponType": "mage"
			}
		],
		"start": "2023-06-28 12:00:00",
		"end": "2023-07-18 14:59:59"
	},
	{
		"version": "1.1.1",
		"items": [
			{
				"itemId": 710,
				"imageUrl": "/hsr/UI/avatarshopicon/1006.webp",
				"itemType": "Character",
				"name": "银狼",
				"nameEn": "Silver Wolf",
				"damageType": "quantum",
				"element": "quantum",
				"rankType": 5,
				"avatarBaseType": "nihility",
				"weaponType": "warlock"
			},
			{
				"itemId": 8,
				"imageUrl": "/hsr/UI/avatarshopicon/1002.webp",
				"itemType": "Character",
				"name": "丹恒",
				"nameEn": "Dan Heng",
				"damageType": "wind",
				"element": "wind",
				"rankType": 4,
				"avatarBaseType": "hunt",
				"weaponType": "rogue"
			},
			{
				"itemId": 12,
				"imageUrl": "/hsr/UI/avatarshopicon/1009.webp",
				"itemType": "Character",
				"name": "艾丝妲",
				"nameEn": "Asta",
				"damageType": "fire",
				"element": "fire",
				"rankType": 4,
				"avatarBaseType": "harmony",
				"weaponType": "shaman"
			},
			{
				"itemId": 16,
				"imageUrl": "/hsr/UI/avatarshopicon/1103.webp",
				"itemType": "Character",
				"name": "希露瓦",
				"nameEn": "Serval",
				"damageType": "lightning",
				"element": "thunder",
				"rankType": 4,
				"avatarBaseType": "erudition",
				"weaponType": "mage"
			}
		],
		"start": "2023-06-07 06:00:00",
		"end": "2023-06-28 11:59:59"
	},
	{
		"version": "1.0.2",
		"items": [
			{
				"itemId": 26,
				"imageUrl": "/hsr/UI/avatarshopicon/1204.webp",
				"itemType": "Character",
				"name": "景元",
				"nameEn": "Jing Yuan",
				"damageType": "lightning",
				"element": "thunder",
				"rankType": 5,
				"avatarBaseType": "erudition",
				"weaponType": "mage"
			},
			{
				"itemId": 25,
				"imageUrl": "/hsr/UI/avatarshopicon/1202.webp",
				"itemType": "Character",
				"name": "停云",
				"nameEn": "Tingyun",
				"damageType": "lightning",
				"element": "thunder",
				"rankType": 4,
				"avatarBaseType": "harmony",
				"weaponType": "shaman"
			},
			{
				"itemId": 27,
				"imageUrl": "/hsr/UI/avatarshopicon/1206.webp",
				"itemType": "Character",
				"name": "素裳",
				"nameEn": "Sushang",
				"damageType": "physical",
				"element": "physical",
				"rankType": 4,
				"avatarBaseType": "hunt",
				"weaponType": "rogue"
			},
			{
				"itemId": 7,
				"imageUrl": "/hsr/UI/avatarshopicon/1224.webp",
				"itemType": "Character",
				"name": "三月七 - 存护",
				"nameEn": "March 7th",
				"damageType": "ice",
				"element": "ice",
				"rankType": 4,
				"avatarBaseType": "preservation",
				"weaponType": "knight"
			}
		],
		"start": "2023-05-17 18:00:00",
		"end": "2023-06-06 14:59:59"
	},
	{
		"version": "1.0.1",
		"items": [
			{
				"itemId": 15,
				"imageUrl": "/hsr/UI/avatarshopicon/1102.webp",
				"itemType": "Character",
				"name": "希儿",
				"nameEn": "Seele",
				"damageType": "quantum",
				"element": "quantum",
				"rankType": 5,
				"avatarBaseType": "hunt",
				"weaponType": "rogue"
			},
			{
				"itemId": 18,
				"imageUrl": "/hsr/UI/avatarshopicon/1105.webp",
				"itemType": "Character",
				"name": "娜塔莎",
				"nameEn": "Natasha",
				"damageType": "physical",
				"element": "physical",
				"rankType": 4,
				"avatarBaseType": "abundance",
				"weaponType": "priest"
			},
			{
				"itemId": 22,
				"imageUrl": "/hsr/UI/avatarshopicon/1109.webp",
				"itemType": "Character",
				"name": "虎克",
				"nameEn": "Hook",
				"damageType": "fire",
				"element": "fire",
				"rankType": 4,
				"avatarBaseType": "destruction",
				"weaponType": "warrior"
			},
			{
				"itemId": 19,
				"imageUrl": "/hsr/UI/avatarshopicon/1106.webp",
				"itemType": "Character",
				"name": "佩拉",
				"nameEn": "Pela",
				"damageType": "ice",
				"element": "ice",
				"rankType": 4,
				"avatarBaseType": "nihility",
				"weaponType": "warlock"
			}
		],
		"start": "2023-04-26 06:00:00",
		"end": "2023-05-17 17:59:59"
	}
]